mypsl/__init__.py
mypsl/cli.py
mypsl/libs/__init__.py
mypsl/libs/_version.py
mypsl/libs/connections.py
mypsl/libs/exceptions.py
mypsl/libs/mysqldriver.py
mypsl/libs/notification.py
mypsl/libs/outputter.py
mypsl/libs/processlist.py
mypsl/libs/processnode.py
mypsl-0.32.dist-info/LICENSE
mypsl-0.32.dist-info/METADATA
mypsl-0.32.dist-info/WHEEL
mypsl-0.32.dist-info/entry_points.txt
mypsl-0.32.dist-info/top_level.txt
mypsl-0.32.dist-info/RECORD
