Metadata-Version: 2.1
Name: mypsl
Version: 0.32
Summary: Whittling down the MySQL process list
Home-page: https://github.com/ksgh/mypsl
Author: Kyle Shenk
Author-email: k.shenk@gmail.com
License: MIT
Platform: UNKNOWN
Classifier: Development Status :: 3 - Alpha
Classifier: License :: OSI Approved :: MIT License
Classifier: Topic :: Software Development :: Build Tools
Classifier: Intended Audience :: Developers
Classifier: Programming Language :: Python :: 2
Classifier: Programming Language :: Python :: 2.6
Classifier: Programming Language :: Python :: 2.7
Requires-Dist: colorama
Requires-Dist: argparse
Requires-Dist: argcomplete
Requires-Dist: pymysql
Requires-Dist: slackclient
